setup.py
dm/__init__.py
dm.incrementalsearch.egg-info/PKG-INFO
dm.incrementalsearch.egg-info/SOURCES.txt
dm.incrementalsearch.egg-info/dependency_links.txt
dm.incrementalsearch.egg-info/namespace_packages.txt
dm.incrementalsearch.egg-info/not-zip-safe
dm.incrementalsearch.egg-info/requires.txt
dm.incrementalsearch.egg-info/top_level.txt
dm/incrementalsearch/LICENSE.txt
dm/incrementalsearch/README.txt
dm/incrementalsearch/VERSION.txt
dm/incrementalsearch/__init__.py
dm/incrementalsearch/_isearch.c
dm/incrementalsearch/_isearch.h
dm/incrementalsearch/_isearch_int.c
dm/incrementalsearch/_isearch_long.c
dm/incrementalsearch/_isearch_obj.c
dm/incrementalsearch/_isearch_template.c
dm/incrementalsearch/btrees_structs.h
dm/incrementalsearch/tests/__init__.py
dm/incrementalsearch/tests/testIBTrees.py
dm/incrementalsearch/tests/testISearch.py