Metadata-Version: 1.1
Name: dm.incrementalsearch
Version: 3.0
Summary: An efficient low level search execution engine on top of ZODB.BTrees.
Home-page: https://pypi.org/project/dm.incrementalsearch
Author: Dieter Maurer
Author-email: dieter@handshake.de
License: BSD (see "dm/incrementalsearch/LICENSE.txt", for details)
Keywords: search,efficient,ZODB,incremental,BTrees
Platform: UNKNOWN
Classifier: Development Status :: 5 - Production/Stable
Classifier: Intended Audience :: Developers
Classifier: License :: OSI Approved :: BSD License
Classifier: Framework :: ZODB
Classifier: Operating System :: OS Independent
Classifier: Programming Language :: Python
Classifier: Programming Language :: Python :: 2.7
Classifier: Programming Language :: Python :: 3
Classifier: Programming Language :: Python :: Implementation :: CPython
Classifier: Programming Language :: C
Classifier: Topic :: Utilities
